mcp_lite/__init__.py
mcp_lite/mcp.py
mcp_lite/tool.py
mcp_lite-0.1.0.dist-info/licenses/LICENSE
mcp_lite-0.1.0.dist-info/METADATA
mcp_lite-0.1.0.dist-info/WHEEL
mcp_lite-0.1.0.dist-info/top_level.txt
mcp_lite-0.1.0.dist-info/RECORD
