Metadata-Version: 2.4
Name: mcp-lite
Version: 0.1.0
Summary: The library for local work with AI tools without running MCP server.
Author-email: Aleksei Fomenko <fomenko_ai@proton.me>
License: MIT
Project-URL: Homepage, https://github.com/fomenko-ai/mcp-lite
Project-URL: Repository, https://github.com/fomenko-ai/mcp-lite
Project-URL: Issues, https://github.com/fomenko-ai/mcp-lite/issues
Classifier: Programming Language :: Python :: 3
Classifier: License :: OSI Approved :: MIT License
Requires-Python: >=3.8
License-File: LICENSE
Dynamic: license-file
